{"nodes":[{"id":"alert_civique_front_server_utils_helpers_js","label":"helpers","source_file":".\\alert_civique_front\\server\\utils\\helpers.js","node_type":"file"},{"id":"alert_civique_front_server_utils_helpers_js_getlocalips","label":"getLocalIPs()","source_file":".\\alert_civique_front\\server\\utils\\helpers.js","source_location":"L3","node_type":"function"},{"id":"alert_civique_front_server_utils_helpers_js_formatbytes","label":"formatBytes()","source_file":".\\alert_civique_front\\server\\utils\\helpers.js","source_location":"L18","node_type":"function"}],"edges":[{"source":"alert_civique_front_server_utils_helpers_js","target":"alert_civique_front_server_utils_helpers_js_getlocalips","relation":"defines","confidence":"EXTRACTED","confidence_score":1.0,"source_file":".\\alert_civique_front\\server\\utils\\helpers.js","source_location":"L3","weight":1.0},{"source":"alert_civique_front_server_utils_helpers_js","target":"alert_civique_front_server_utils_helpers_js_formatbytes","relation":"defines","confidence":"EXTRACTED","confidence_score":1.0,"source_file":".\\alert_civique_front\\server\\utils\\helpers.js","source_location":"L18","weight":1.0}],"hyperedges":[]}